spdown/__init__.py
spdown/__main__.py
spdown/config.py
spdown/secrets.py
spdown/spotify.py
spdown/track.py
spdown/youtube.py
spdown-1.0.0.data/scripts/spdown
spdown-1.0.0.dist-info/DESCRIPTION.rst
spdown-1.0.0.dist-info/METADATA
spdown-1.0.0.dist-info/RECORD
spdown-1.0.0.dist-info/WHEEL
spdown-1.0.0.dist-info/metadata.json
spdown-1.0.0.dist-info/top_level.txt
test/__init__.py
test/test_all.py
test/test_config.py
test/test_secrets.py
test/test_spotify.py
test/test_youtube.py
