Metadata-Version: 2.0
Name: spdown
Version: 1.0.0
Summary: Download Spotify playlists from YouTube
Home-page: https://github.com/beremaran/spdown
Author: Berke Emrecan Arslan
Author-email: berke@beremaran.com
License: UNKNOWN
Keywords: youtube spotify spotify-api spotify-playlist
Platform: UNKNOWN
Classifier: Programming Language :: Python :: 3
Classifier: License :: OSI Approved :: MIT License
Classifier: Operating System :: OS Independent
Requires-Dist: youtube-dl
Requires-Dist: google-api-python-client
Requires-Dist: google-auth
Requires-Dist: spotipy
Requires-Dist: eyed3
Requires-Dist: py-lru-cache
